ordereduuid/__init__.py
ordereduuid/ordereduuid.py
tests/__init__.py
tests/test_ordereduuid.py
ordereduuid-0.5.0.dist-info/LICENSE
ordereduuid-0.5.0.dist-info/METADATA
ordereduuid-0.5.0.dist-info/WHEEL
ordereduuid-0.5.0.dist-info/top_level.txt
ordereduuid-0.5.0.dist-info/RECORD
